europe_pmc/__init__.py
europe_pmc/version.json
europe_pmc/bin/__init__.py
europe_pmc/bin/main.py
europe_pmc/core/__init__.py
europe_pmc/core/api.py
europe_pmc/util/__init__.py
europe_pmc-1.0.0.dist-info/METADATA
europe_pmc-1.0.0.dist-info/WHEEL
europe_pmc-1.0.0.dist-info/entry_points.txt
europe_pmc-1.0.0.dist-info/top_level.txt
europe_pmc-1.0.0.dist-info/RECORD
