Metadata-Version: 2.1
Name: europe-pmc
Version: 1.0.0
Summary: Open Access PDF Downloader with EuropePMC
Home-page: https://www.github.com/suqingdong/europe_pmc
Author: suqingdong
Author-email: suqingdong1114@gmail.com
License: MIT License
Platform: UNKNOWN
Classifier: Development Status :: 5 - Production/Stable
Classifier: Operating System :: OS Independent
Classifier: Intended Audience :: Developers
Classifier: License :: OSI Approved :: MIT License
Classifier: Programming Language :: Python
Classifier: Programming Language :: Python :: 3
Classifier: Programming Language :: Python :: 3.8
Classifier: Programming Language :: Python :: 3.9
Classifier: Topic :: Software Development :: Libraries
Requires-Dist: tqdm
Requires-Dist: click
Requires-Dist: requests
Requires-Dist: simple-loggers
Requires-Dist: human-readable
